tabula_mutabilis/__init__.py
tabula_mutabilis/controllers.py
tabula_mutabilis/editors.py
tabula_mutabilis/model.py
tabula_mutabilis/property_grid.py
tabula_mutabilis/py.typed
tabula_mutabilis/style_editor.py
tabula_mutabilis/styles.py
tabula_mutabilis/views.py
tabula_mutabilis/widgets.py
tabula_mutabilis-100.20.dist-info/METADATA
tabula_mutabilis-100.20.dist-info/WHEEL
tabula_mutabilis-100.20.dist-info/top_level.txt
tabula_mutabilis-100.20.dist-info/RECORD
